core_models/__init__.py
core_models/api_response.py
core_models/base_views.py
core_models/constants.py
core_models/settings.example.py
core_models/settings.py
core_models/utils.py
core_models/app/__init__.py
core_models/app/admin.py
core_models/app/apps.py
core_models/app/context_processors.py
core_models/app/integrations/__init__.py
core_models/app/integrations/base_integration.py
core_models/app/integrations/verto/__init__.py
core_models/app/integrations/verto/add_beneficiary.py
core_models/app/integrations/verto/create_fx_trade.py
core_models/app/integrations/verto/create_payment.py
core_models/app/integrations/verto/get_currencies.py
core_models/app/integrations/verto/get_fx_rate.py
core_models/app/integrations/verto/get_purposes.py
core_models/app/integrations/verto/get_wallets.py
core_models/app/integrations/verto/login.py
core_models/app/managers/__init__.py
core_models/app/managers/notification_manager.py
core_models/app/migrations/0001_initial.py
core_models/app/migrations/0002_alter_user_name_alter_user_phone_number.py
core_models/app/migrations/0003_alter_user_onboarding_stage.py
core_models/app/migrations/0004_user_reset_token_user_reset_token_expiry.py
core_models/app/migrations/0005_remove_bankaccount_user_remove_user_name_and_more.py
core_models/app/migrations/0006_currency_invoice_alter_company_options_invoiceitem.py
core_models/app/migrations/0007_remove_invoice_paid_invoice_status_invoice_subtotal_and_more.py
core_models/app/migrations/0008_alter_contract_options_contract_status_and_more.py
core_models/app/migrations/0009_alter_currency_options_alter_companydocument_company.py
core_models/app/migrations/0010_rename_discount_invoice_interest_and_more.py
core_models/app/migrations/0011_remove_invoice_draft_company_annual_turnover_and_more.py
core_models/app/migrations/0012_rename_amount_invoiceitem_total_invoice_discount_and_more.py
core_models/app/migrations/0013_country_region_subregion_city_alter_company_city_and_more.py
core_models-0.5.7.dist-info/LICENSE
core_models-0.5.7.dist-info/METADATA
core_models-0.5.7.dist-info/WHEEL
core_models-0.5.7.dist-info/top_level.txt
core_models-0.5.7.dist-info/RECORD
