Metadata-Version: 2.1
Name: core_models
Version: 0.5.7
Summary: Liquify core package
Author: Folayemi Bello
Author-email: <bello.folayemi.az@gmail.com>
Keywords: python,liquify
Classifier: Programming Language :: Python :: 3
Classifier: License :: OSI Approved :: MIT License
Classifier: Operating System :: OS Independent
License-File: LICENSE
Requires-Dist: django
Requires-Dist: python-dotenv
Requires-Dist: django-safedelete
Requires-Dist: redis
Requires-Dist: django-environ
Requires-Dist: onesignal-sdk
Requires-Dist: django-cities-light
Requires-Dist: daphne
Requires-Dist: psycopg2-binary
Requires-Dist: django-slack
Requires-Dist: uvicorn
Requires-Dist: django-storages
Requires-Dist: boto3
Requires-Dist: dj-database-url
Requires-Dist: django-model-utils
Requires-Dist: django-ckeditor-5
Requires-Dist: django-quill-editor
